{
  "name": {
    "en": "Electricity Meter"
  },
  "class": "sensor",
  "capabilities": [
    "octopus_price",
    "octopus_price_level",
    "meter_power",
    "octopus_usage_today",
    "octopus_cost_today",
    "octopus_standing_charge",
    "octopus_balance"
  ],
  "capabilitiesOptions": {
    "meter_power": {
      "title": {
        "en": "Total consumption"
      }
    }
  },
  "energy": {
    "cumulative": true,
    "cumulativeImportedCapability": "meter_power"
  },
  "platforms": [
    "local"
  ],
  "connectivity": [
    "cloud"
  ],
  "images": {
    "small": "/drivers/electricity/assets/images/small.png",
    "large": "/drivers/electricity/assets/images/large.png",
    "xlarge": "/drivers/electricity/assets/images/xlarge.png"
  },
  "pair": [
    {
      "id": "start"
    },
    {
      "id": "list_devices",
      "template": "list_devices",
      "navigation": {
        "next": "add_devices"
      }
    },
    {
      "id": "add_devices",
      "template": "add_devices"
    }
  ],
  "repair": [
    {
      "id": "start"
    }
  ],
  "settings": [
    {
      "id": "poll_interval",
      "type": "number",
      "label": {
        "en": "Refresh interval (minutes)"
      },
      "value": 30,
      "min": 5,
      "max": 1440,
      "hint": {
        "en": "How often to refresh prices, usage and balance. Prices update once per half hour."
      }
    },
    {
      "id": "vat",
      "type": "dropdown",
      "label": {
        "en": "Prices include VAT"
      },
      "value": "inc",
      "hint": {
        "en": "Whether displayed unit rates and standing charges include 5% VAT."
      },
      "values": [
        { "id": "inc", "label": { "en": "Including VAT" } },
        { "id": "exc", "label": { "en": "Excluding VAT" } }
      ]
    },
    {
      "id": "cheap_threshold",
      "type": "number",
      "label": {
        "en": "\"Cheap\" price threshold (p/kWh)"
      },
      "value": 15,
      "min": -50,
      "max": 200,
      "hint": {
        "en": "At or below this unit rate the price level is considered cheap."
      }
    },
    {
      "id": "expensive_threshold",
      "type": "number",
      "label": {
        "en": "\"Expensive\" price threshold (p/kWh)"
      },
      "value": 30,
      "min": -50,
      "max": 200,
      "hint": {
        "en": "At or above this unit rate the price level is considered expensive."
      }
    },
    {
      "id": "live_power",
      "type": "checkbox",
      "label": {
        "en": "Live power (Octopus Home Mini)"
      },
      "value": false,
      "hint": {
        "en": "If you have an Octopus Home Mini, show near real-time power (W). Polls every 30 seconds."
      }
    }
  ]
}
